membit_mcp.py
membit_mcp-0.1.8.dist-info/METADATA
membit_mcp-0.1.8.dist-info/WHEEL
membit_mcp-0.1.8.dist-info/entry_points.txt
membit_mcp-0.1.8.dist-info/RECORD
