Metadata-Version: 2.3
Name: membit-mcp
Version: 0.1.8
Summary: Membit MCP Server for accessing real-time social data via Membit's API
License: MIT
Author: Paul Nattapatsiri
Author-email: paul@bandprotocol.com
Requires-Python: >=3.10
Classifier: License :: OSI Approved :: MIT License
Classifier: Programming Language :: Python :: 3
Classifier: Programming Language :: Python :: 3.10
Classifier: Programming Language :: Python :: 3.11
Classifier: Programming Language :: Python :: 3.12
Classifier: Programming Language :: Python :: 3.13
Requires-Dist: mcp[cli] (>=1.3.0)
